gempaterkini/__init__.py
latestinfoearthquakeindonesia-0.0.5.dist-info/LICENSE
latestinfoearthquakeindonesia-0.0.5.dist-info/METADATA
latestinfoearthquakeindonesia-0.0.5.dist-info/WHEEL
latestinfoearthquakeindonesia-0.0.5.dist-info/top_level.txt
latestinfoearthquakeindonesia-0.0.5.dist-info/RECORD
