Metadata-Version: 2.1
Name: latestinfoearthquakeindonesia
Version: 0.0.5
Summary: This package will get the latest earthquake from BMKG | Meteorological, Climatological, and Geophysical Agency.
Home-page: https://github.com/TOSS-ID/latest-indonesia-earthquake
Author: Hendra Go
Author-email: hendrago91@gmail.com
Classifier: Programming Language :: Python :: 3
Classifier: License :: OSI Approved :: GNU General Public License v3 (GPLv3)
Classifier: Operating System :: OS Independent
Classifier: Development Status :: 5 - Production/Stable
Requires-Python: >=3.6
License-File: LICENSE
